mt5_remote/__init__.py
mt5_remote/__main__.py
mt5_remote-1.0.5.dist-info/licenses/LICENSE.txt
mt5_remote-1.0.5.dist-info/METADATA
mt5_remote-1.0.5.dist-info/WHEEL
mt5_remote-1.0.5.dist-info/top_level.txt
mt5_remote-1.0.5.dist-info/RECORD
