Metadata-Version: 2.4
Name: mt5_remote
Version: 1.0.5
Summary: MetaTrader5 with remote access using a client/server architecture
Author: BigMitchGit
License-Expression: MIT
Project-URL: Homepage, https://github.com/bigmitchgit/mt5_remote
Classifier: Programming Language :: Python :: 3
Classifier: Programming Language :: Python :: 3 :: Only
Classifier: Operating System :: OS Independent
Requires-Python: >=3.11
License-File: LICENSE.txt
Requires-Dist: numpy==2.3.2
Requires-Dist: plumbum==1.9.0
Requires-Dist: rpyc==6.0.2
Requires-Dist: metatrader5==5.0.5200; sys_platform == "win32"
Requires-Dist: pywin32==311; sys_platform == "win32"
Provides-Extra: server
Requires-Dist: metatrader5==5.0.5200; extra == "server"
Requires-Dist: pywin32==311; extra == "server"
Dynamic: license-file
